vaultsfyi/__init__.py
vaultsfyi/client.py
vaultsfyi/exceptions.py
vaultsfyi/py.typed
vaultsfyi/utils.py
vaultsfyi-1.2.0.dist-info/licenses/LICENSE
vaultsfyi-1.2.0.dist-info/METADATA
vaultsfyi-1.2.0.dist-info/WHEEL
vaultsfyi-1.2.0.dist-info/top_level.txt
vaultsfyi-1.2.0.dist-info/RECORD
