Metadata-Version: 2.4
Name: vaultsfyi
Version: 1.2.0
Summary: A Python SDK for interacting with the Vaults.fyi API
Author-email: Kaimi Seeker <kaimi@wallfacer.io>
License: MIT
Project-URL: Homepage, https://github.com/wallfacerlabs/python-sdk
Project-URL: Bug Reports, https://github.com/wallfacerlabs/python-sdk/issues
Project-URL: Source, https://github.com/wallfacerlabs/python-sdk
Project-URL: Documentation, https://github.com/wallfacerlabs/python-sdk#readme
Keywords: defi,vaults,yield,ethereum,web3,crypto
Classifier: Development Status :: 4 - Beta
Classifier: Intended Audience :: Developers
Classifier: License :: OSI Approved :: MIT License
Classifier: Operating System :: OS Independent
Classifier: Programming Language :: Python :: 3
Classifier: Programming Language :: Python :: 3.8
Classifier: Programming Language :: Python :: 3.9
Classifier: Programming Language :: Python :: 3.10
Classifier: Programming Language :: Python :: 3.11
Classifier: Programming Language :: Python :: 3.12
Requires-Python: >=3.8
License-File: LICENSE
Requires-Dist: requests>=2.25.0
Dynamic: license-file
